README.md
setup.py
deepc_hunt/__init__.py
deepc_hunt/controllers.py
deepc_hunt/utils.py
deepc_hunt.egg-info/PKG-INFO
deepc_hunt.egg-info/SOURCES.txt
deepc_hunt.egg-info/dependency_links.txt
deepc_hunt.egg-info/requires.txt
deepc_hunt.egg-info/top_level.txt