Metadata-Version: 2.1
Name: deepc-hunt
Version: 0.0.6
Summary: PyTorch module for DeePC
Home-page: https://github.com/michael-cummins/DeePC-HUNT
Author: Michael Cummins
Classifier: Programming Language :: Python :: 3
